snapbatch/__init__.py
snapbatch/cli.py
snapbatch/tools.py
snapbatch/launcher/__init__.py
snapbatch/launcher/constants.py
snapbatch/launcher/launch.py
snapbatch/launcher/multinode_runner.py
snapbatch/launcher/runner.py
snapbatch-0.4.0.data/scripts/snapbatch_purge
snapbatch-0.4.0.dist-info/METADATA
snapbatch-0.4.0.dist-info/WHEEL
snapbatch-0.4.0.dist-info/entry_points.txt
snapbatch-0.4.0.dist-info/top_level.txt
snapbatch-0.4.0.dist-info/RECORD
