Metadata-Version: 2.1
Name: snapbatch
Version: 0.4.0
Summary: `snapbatch` is a replacement of `sbatch` to create a snapshot of current working directory, and submit the command to `sbatch`.
Home-page: https://github.com/Sleepychord/snapbatch
Author: Ming Ding
Author-email: mingding.thu@gmail.com
License: MIT license
Requires-Python: >=3.5
Requires-Dist: GitPython
